{
  "module_slug": "chained-reads-intro",
  "title": "Chained Reads — Two Reads in a Row",
  "concept_id": "hunt_the_advantage",
  "category": "OFFENSE",
  "order": 15,
  "prerequisite_module_ids": ["advantage-or-reset", "skip-the-rotation"],
  "lesson": {
    "order": 1,
    "title": "The first action is the question. The second action is the answer.",
    "body_md": "## What is a chained read?\n\nEvery decoder you have learned so far is **one read**. You see one cue, you make one decision: drive on a late closeout, cut on a hand in the lane, skip when the help over-rotates. **SKR is one read. HUNT is two reads in a row.**\n\nA chained read says: my first action created a problem the defense had to solve. The way they solved it gave me something new. *That* new thing is what I actually attack.\n\n```takeaway\nHUNT teaches the rhythm: action → reaction → read → action. The first action sets the trap. The second action is the score.\n```\n\n## Why decoy actions matter\n\nIn a single-read decoder the first move is the move. In a chained read the first move is **bait**. The screen, the skip, the cut — sometimes its only job is to make the defense move. Once the defense moves, the geometry changes. The new geometry is the read.\n\nA player who treats every first action like the score lives in single-read cognition. A player who treats the first action like a question — *what will the defense give me?* — has crossed into chained reads.\n\n```tip\nWhen the first action does not create a clean shot, do not panic. Watch what the defense did. The answer is in the reaction.\n```\n\n## The four moves of a chained read\n\n1. **Action.** You do something — set or use a screen, throw a skip, run a hard cut. Something that forces the defense to choose.\n2. **Reaction.** The defense responds. A switch happens, a closeout flies, a tag commits. Their bodies move because they have to.\n3. **Read.** You look at what the reaction left behind. A slower defender on you. A late closeout angle. A vacated paint. The read is the *new* geometry, not the old one.\n4. **Action.** You take what the reaction gave you. This is the decision beat — drive the recovery foot, skip to the now-open shooter, cut into the abandoned space.\n\n```takeaway\nFour beats, but only one decision. Steps 1 and 2 set the table; step 3 is where you look; step 4 is where you commit.\n```\n\n## How HUNT scenarios look on screen\n\nA HUNT scenario freezes the play **twice**. The first freeze (about one second long) is observation only — you see the matchup or the action that just happened. There is no choice tray yet. Then the defense reacts in real time. Then the play freezes again. The second freeze is the decision beat — the choice tray opens here, and you pick.\n\nDo not try to answer on the first freeze. Beat one is for looking. Beat two is for choosing.\n\n```tip\nLet your eyes track the defender between the two freezes. The cue you need at beat two is hiding in the way they moved.\n```\n\n## SKR vs HUNT — the cleanest way to keep them apart\n\nSKR (Skip the Rotation) is one read: the help over-rotates, you skip past it. HUNT chains that idea: the first action *forces* the rotation, then you read what the over-rotation left open. Same cues, twice the cognition.\n\n- **SKR:** defender is already out of position when the play starts. Read once, act once.\n- **HUNT:** defender becomes out of position because of your first action. Read what they were, read what they became, then act.\n\n```mistake\nTrying to solve a HUNT scenario on the first freeze.\nFix: beat one is observation. Wait for the second freeze. The choice tray will open when it is your turn.\n```\n\n## Self-check after the rep\n\n```reveal\nQ: Did I wait for the second freeze before I picked?\nA: Beat one is for looking. Beat two is for choosing. If you answered on beat one you skipped half the read.\n```\n\n```reveal\nQ: Did I track the defender between the freezes?\nA: The reaction is the load-bearing part. The new cue at beat two is the one their body just created.\n```\n\n```reveal\nQ: When I missed, was it at the reaction or the read?\nA: Missing at the reaction means you stopped watching after beat one. Missing at the read means the new cue was there and you did not see it.\n```\n\n## Try it\n\n```quiz\nQ: A screen forces the defense to switch. A smaller defender is now on you. His recovery foot points toward half-court. What is the read?\n- Pass the ball out and re-set ✗\n- Drive baseline against his recovery foot ✓\n- Drive at the help defender behind him ✗\nWhy: The switch is the reaction. His recovery foot is the new cue. Attack the side his foot is pointing away from.\n```\n\n```coach\nGreat offense is two-step thinking. Make them move. Then take what they gave you.\n```"
  }
}
